Metadata-Version: 1.2
Name: tseries-patterns
Version: 0.1
Summary: Momentum / Trend labeling for financial timeseries
Home-page: https://github.com/tr8dr/tseries-patterns
Author: Jonathan Shore
Author-email: jonathan.shore@gmail.com
License: MIT License
Download-URL: https://github.com/tr8dr/tseries-patterns/archive/V0_1.tar.gz
Project-URL: Bug Reports, https://github.com/tr8dr/tseries-patterns/issues
Project-URL: Source, https://github.com/tr8dr/tseries-patterns
Project-URL: Documentation, https://github.com/tr8dr/tseries-patterns
Keywords: trend detection,financial trends,quant,stocks,trading
Platform: UNKNOWN
Classifier: Development Status :: 4 - Beta
Classifier: Programming Language :: Python :: 3 :: Only
Classifier: Programming Language :: Python :: 3.6
Classifier: Programming Language :: Python :: 3.7
Classifier: Programming Language :: Python :: 3.8
Classifier: License :: OSI Approved :: MIT License
Classifier: Intended Audience :: Developers
Classifier: Topic :: Office/Business :: Financial
Classifier: Topic :: Office/Business :: Financial :: Investment
Classifier: Topic :: Scientific/Engineering :: Information Analysis
Classifier: Topic :: Software Development :: Libraries
Requires-Python: >=3
